picoboot/__init__.py
picoboot/_version.py
picoboot/picoboot.py
picoboot/picobootmonitor.py
picoboot/utils.py
picoboot/core/__init__.py
picoboot/core/enums.py
picoboot/core/exceptions.py
picoboot/core/log.py
picoboot/tools/picotool.py
pypicoboot-1.5.dist-info/METADATA
pypicoboot-1.5.dist-info/WHEEL
pypicoboot-1.5.dist-info/top_level.txt
pypicoboot-1.5.dist-info/RECORD
