Metadata-Version: 2.4
Name: pypicoboot
Version: 1.5
Summary: Pico Boot for Python
Home-page: https://github.com/polhenarejos/pypicoboot
Author: Pol Henarejos
Author-email: Pol Henarejos <pol.henarejos@cttc.es>
License:                     GNU AFFERO GENERAL PUBLIC LICENSE
Project-URL: Homepage, https://github.com/polhenarejos/pypicoboot
Classifier: Development Status :: 5 - Production/Stable
Classifier: Environment :: Plugins
Classifier: Intended Audience :: System Administrators
Classifier: License :: OSI Approved :: GNU Affero General Public License v3 or later (AGPLv3+)
Classifier: Programming Language :: Python :: 3.8
Classifier: Topic :: Security
Classifier: Topic :: System :: Installation/Setup
Classifier: Topic :: System :: Networking
Classifier: Topic :: System :: Systems Administration
Classifier: Topic :: Utilities
Requires-Python: >=2.7, !=3.0.*, !=3.1.*, !=3.2.*, !=3.3.*, !=3.4.*, !=3.5.*
Requires-Dist: setuptools
Requires-Dist: pyusb
Dynamic: author
Dynamic: home-page
Dynamic: requires-python
